Workbook

Sheet Premissas
A1: viço — Modelo financeiro (cenário base)
A2: Células em amarelo são premissas editáveis. Todo o resto é fórmula.
A4: Premissa | B4: Valor | C4: Fonte / observação
A5: Preço plano mensal (R$) | B5: 24.9 | C5: Stripe vico_monthly
A6: Preço plano anual (R$) | B6: 199 | C6: Stripe vico_yearly
A7: Mix de novos assinantes no anual | B7: 0.6 | C7: Hipótese; anual pré-selecionado no paywall
A8: Taxa de loja/gateway (média) | B8: 0.1 | C8: Mix web (Stripe ~4%) e lojas (15% Small Business)
A9: Impostos sobre receita | B9: 0.11 | C9: Simples Nacional — validar com contador
A10: Instalação → teste grátis | B10: 0.12 | C10: Hipótese; calibrar no beta
A11: Teste → pagante | B11: 0.4 | C11: RevenueCat 2025: mediana Saúde & Fitness 39,9%
A12: Churn mensal (plano mensal) | B12: 0.12 | C12: Hipótese conservadora para app de consumo
A13: Renovação do plano anual | B13: 0.35 | C13: RevenueCat: planos anuais baratos retêm até 36%
A14: Custo de IA por assinante/mês (R$) | B14: 1.5 | C14: ~8 chamadas de visão/mês; calibrar no AI Gateway
A15: Ticket estudo patrocinado (R$) | B15: 40000 | C15: Hipótese B2B
A16: Ticket painel de tendências (R$/mês) | B16: 8000 | C16: Hipótese B2B
A19: Premissas por ano
A20: Item | B20: Ano 1 | C20: Ano 2 | D20: Ano 3 | E20: Ano 4 | F20: Ano 5
A21: Custo por instalação paga (R$) | B21: 4 | C21: 4.5 | D21: 5 | E21: 5.5 | F21: 6
A22: Marketing (R$/mês) | B22: 25000 | C22: 110000 | D22: 240000 | E22: 380000 | F22: 520000
A23: Instalações orgânicas por paga | B23: 0.4 | C23: 0.7 | D23: 1 | E23: 1.2 | F23: 1.4
A24: Equipe (R$/mês) | B24: 22000 | C24: 85000 | D24: 170000 | E24: 260000 | F24: 350000
A25: Administrativo (R$/mês) | B25: 5000 | C25: 12000 | D25: 20000 | E25: 30000 | F25: 40000
A26: Infra e ferramentas (R$/mês) | B26: 1500 | C26: 4000 | D26: 9000 | E26: 15000 | F26: 22000
A27: Estudos patrocinados (qtd/ano) | B27: 0 | C27: 4 | D27: 10 | E27: 16 | F27: 24
A28: Clientes do painel B2B | B28: 0 | C28: 0 | D28: 3 | E28: 6 | F28: 10
A29: Comissão afiliados por assinante (R$/mês) | B29: 0.4 | C29: 0.8 | D29: 1 | E29: 1.2 | F29: 1.3

Sheet Anual
A1: Resumo anual
A3: Indicador | B3: Ano 1 | C3: Ano 2 | D3: Ano 3 | E3: Ano 4 | F3: Ano 5
A4: Novos assinantes | B4: =SUM(Mensal!D2:D13) | C4: =SUM(Mensal!D14:D25) | D4: =SUM(Mensal!D26:D37) | E4: =SUM(Mensal!D38:D49) | F4: =SUM(Mensal!D50:D61)
A5: Assinantes ativos (fim do ano) | B5: =Mensal!K13 | C5: =Mensal!K25 | D5: =Mensal!K37 | E5: =Mensal!K49 | F5: =Mensal!K61
A6: ARR de assinaturas (fim do ano) | B6: =Mensal!L13*12 | C6: =Mensal!L25*12 | D6: =Mensal!L37*12 | E6: =Mensal!L49*12 | F6: =Mensal!L61*12
A7: Receita bruta | B7: =SUM(Mensal!N2:N13) | C7: =SUM(Mensal!N14:N25) | D7: =SUM(Mensal!N26:N37) | E7: =SUM(Mensal!N38:N49) | F7: =SUM(Mensal!N50:N61)
A8: de assinaturas | B8: =SUM(Mensal!L2:L13) | C8: =SUM(Mensal!L14:L25) | D8: =SUM(Mensal!L26:L37) | E8: =SUM(Mensal!L38:L49) | F8: =SUM(Mensal!L50:L61)
A9: B2B (afiliados, estudos, painel) | B9: =SUM(Mensal!M2:M13) | C9: =SUM(Mensal!M14:M25) | D9: =SUM(Mensal!M26:M37) | E9: =SUM(Mensal!M38:M49) | F9: =SUM(Mensal!M50:M61)
A10: Receita líquida | B10: =SUM(Mensal!Q2:Q13) | C10: =SUM(Mensal!Q14:Q25) | D10: =SUM(Mensal!Q26:Q37) | E10: =SUM(Mensal!Q38:Q49) | F10: =SUM(Mensal!Q50:Q61)
A11: Custo de IA | B11: =SUM(Mensal!R2:R13) | C11: =SUM(Mensal!R14:R25) | D11: =SUM(Mensal!R26:R37) | E11: =SUM(Mensal!R38:R49) | F11: =SUM(Mensal!R50:R61)
A12: Marketing | B12: =SUM(Mensal!S2:S13) | C12: =SUM(Mensal!S14:S25) | D12: =SUM(Mensal!S26:S37) | E12: =SUM(Mensal!S38:S49) | F12: =SUM(Mensal!S50:S61)
A13: Equipe | B13: =SUM(Mensal!T2:T13) | C13: =SUM(Mensal!T14:T25) | D13: =SUM(Mensal!T26:T37) | E13: =SUM(Mensal!T38:T49) | F13: =SUM(Mensal!T50:T61)
A14: Administrativo + infra | B14: =SUM(Mensal!U2:V13) | C14: =SUM(Mensal!U14:V25) | D14: =SUM(Mensal!U26:V37) | E14: =SUM(Mensal!U38:V49) | F14: =SUM(Mensal!U50:V61)
A15: EBITDA | B15: =SUM(Mensal!W2:W13) | C15: =SUM(Mensal!W14:W25) | D15: =SUM(Mensal!W26:W37) | E15: =SUM(Mensal!W38:W49) | F15: =SUM(Mensal!W50:W61)
A16: Margem EBITDA (s/ receita líquida) | B16: =B15/B10 | C16: =C15/C10 | D16: =D15/D10 | E16: =E15/E10 | F16: =F15/F10
A17: Caixa acumulado (sem aporte) | B17: =Mensal!X13 | C17: =Mensal!X25 | D17: =Mensal!X37 | E17: =Mensal!X49 | F17: =Mensal!X61
A20: Necessidade de caixa (pior saldo acumulado) | B20: =-MIN(Mensal!X2:X61)
A21: Mês do pior saldo | B21: =MATCH(MIN(Mensal!X2:X61),Mensal!X2:X61,0)

Sheet Unit economics
A1: Unit economics (por assinante)
A3: ARPU bruto mensal | B3: =Premissas!$B$7*Premissas!$B$6/12+(1-Premissas!$B$7)*Premissas!$B$5
A4: ARPU líquido de taxas, impostos e IA | B4: =B3*(1-Premissas!$B$8-Premissas!$B$9)-Premissas!$B$14
A5: Margem de contribuição | B5: =B4/B3
A6: Vida média (meses) | B6: =(1-Premissas!$B$7)/Premissas!$B$12+Premissas!$B$7*12/(1-Premissas!$B$13)
A7: LTV (contribuição na vida) | B7: =B4*B6
A8: CAC pago — ano 1 | B8: =Mensal!Y2
A9: CAC pago — ano 3 | B9: =Mensal!Y26
A10: LTV / CAC pago — ano 1 | B10: =B7/B8
A11: Payback do CAC pago — ano 1 (meses) | B11: =B8/B4
A12: CAC misto ano 1 (com orgânico) | B12: =B8/(1+INDEX(Premissas!$B$23:$F$23,1,1))
A13: LTV / CAC misto — ano 1 | B13: =B7/B12

Sheet Mensal
A1: Mês | B1: Ano | C1: Instalações | D1: Novos assinantes | E1: Novos mensais | F1: Novos anuais | G1: Ativos mensal | H1: Renovações anuais | I1: Inícios anuais | J1: Ativos anual | K1: Assinantes ativos | L1: Receita assinaturas | M1: Receita B2B | N1: Receita bruta | O1: Taxas de loja | P1: Impostos | Q1: Receita líquida | R1: Custo IA | S1: Marketing | T1: Equipe | U1: Administrativo | V1: Infra | W1: EBITDA | X1: Caixa acumulado | Y1: CAC pago
A2: 1 | B2: =INT((A2-1)/12)+1 | C2: =INDEX(Premissas!$B$22:$F$22,1,B2)/INDEX(Premissas!$B$21:$F$21,1,B2)*(1+INDEX(Premissas!$B$23:$F$23,1,B2)) | D2: =C2*Premissas!$B$10*Premissas!$B$11 | E2: =D2*(1-Premissas!$B$7) | F2: =D2*Premissas!$B$7 | G2: =0*(1-Premissas!$B$12)+E2 | H2: 0 | I2: =F2+H2 | J2: =SUM(I2:I2) | K2: =G2+J2 | L2: =G2*Premissas!$B$5+J2*Premissas!$B$6/12 | M2: =K2*INDEX(Premissas!$B$29:$F$29,1,B2)+INDEX(Premissas!$B$27:$F$27,1,B2)*Premissas!$B$15/12+INDEX(Premissas!$B$28:$F$28,1,B2)*Premissas!$B$16 | N2: =L2+M2 | O2: =L2*Premissas!$B$8 | P2: =N2*Premissas!$B$9 | Q2: =N2-O2-P2 | R2: =K2*Premissas!$B$14 | S2: =INDEX(Premissas!$B$22:$F$22,1,B2) | T2: =INDEX(Premissas!$B$24:$F$24,1,B2) | U2: =INDEX(Premissas!$B$25:$F$25,1,B2) | V2: =INDEX(Premissas!$B$26:$F$26,1,B2) | W2: =Q2-R2-S2-T2-U2-V2 | X2: =0+W2 | Y2: =S2/MAX(S2/INDEX(Premissas!$B$21:$F$21,1,B2)*Premissas!$B$10*Premissas!$B$11,1)
A3: 2 | B3: =INT((A3-1)/12)+1 | C3: =INDEX(Premissas!$B$22:$F$22,1,B3)/INDEX(Premissas!$B$21:$F$21,1,B3)*(1+INDEX(Premissas!$B$23:$F$23,1,B3)) | D3: =C3*Premissas!$B$10*Premissas!$B$11 | E3: =D3*(1-Premissas!$B$7) | F3: =D3*Premissas!$B$7 | G3: =G2*(1-Premissas!$B$12)+E3 | H3: 0 | I3: =F3+H3 | J3: =SUM(I2:I3) | K3: =G3+J3 | L3: =G3*Premissas!$B$5+J3*Premissas!$B$6/12 | M3: =K3*INDEX(Premissas!$B$29:$F$29,1,B3)+INDEX(Premissas!$B$27:$F$27,1,B3)*Premissas!$B$15/12+INDEX(Premissas!$B$28:$F$28,1,B3)*Premissas!$B$16 | N3: =L3+M3 | O3: =L3*Premissas!$B$8 | P3: =N3*Premissas!$B$9 | Q3: =N3-O3-P3 | R3: =K3*Premissas!$B$14 | S3: =INDEX(Premissas!$B$22:$F$22,1,B3) | T3: =INDEX(Premissas!$B$24:$F$24,1,B3) | U3: =INDEX(Premissas!$B$25:$F$25,1,B3) | V3: =INDEX(Premissas!$B$26:$F$26,1,B3) | W3: =Q3-R3-S3-T3-U3-V3 | X3: =X2+W3 | Y3: =S3/MAX(S3/INDEX(Premissas!$B$21:$F$21,1,B3)*Premissas!$B$10*Premissas!$B$11,1)
A4: 3 | B4: =INT((A4-1)/12)+1 | C4: =INDEX(Premissas!$B$22:$F$22,1,B4)/INDEX(Premissas!$B$21:$F$21,1,B4)*(1+INDEX(Premissas!$B$23:$F$23,1,B4)) | D4: =C4*Premissas!$B$10*Premissas!$B$11 | E4: =D4*(1-Premissas!$B$7) | F4: =D4*Premissas!$B$7 | G4: =G3*(1-Premissas!$B$12)+E4 | H4: 0 | I4: =F4+H4 | J4: =SUM(I2:I4) | K4: =G4+J4 | L4: =G4*Premissas!$B$5+J4*Premissas!$B$6/12 | M4: =K4*INDEX(Premissas!$B$29:$F$29,1,B4)+INDEX(Premissas!$B$27:$F$27,1,B4)*Premissas!$B$15/12+INDEX(Premissas!$B$28:$F$28,1,B4)*Premissas!$B$16 | N4: =L4+M4 | O4: =L4*Premissas!$B$8 | P4: =N4*Premissas!$B$9 | Q4: =N4-O4-P4 | R4: =K4*Premissas!$B$14 | S4: =INDEX(Premissas!$B$22:$F$22,1,B4) | T4: =INDEX(Premissas!$B$24:$F$24,1,B4) | U4: =INDEX(Premissas!$B$25:$F$25,1,B4) | V4: =INDEX(Premissas!$B$26:$F$26,1,B4) | W4: =Q4-R4-S4-T4-U4-V4 | X4: =X3+W4 | Y4: =S4/MAX(S4/INDEX(Premissas!$B$21:$F$21,1,B4)*Premissas!$B$10*Premissas!$B$11,1)
A5: 4 | B5: =INT((A5-1)/12)+1 | C5: =INDEX(Premissas!$B$22:$F$22,1,B5)/INDEX(Premissas!$B$21:$F$21,1,B5)*(1+INDEX(Premissas!$B$23:$F$23,1,B5)) | D5: =C5*Premissas!$B$10*Premissas!$B$11 | E5: =D5*(1-Premissas!$B$7) | F5: =D5*Premissas!$B$7 | G5: =G4*(1-Premissas!$B$12)+E5 | H5: 0 | I5: =F5+H5 | J5: =SUM(I2:I5) | K5: =G5+J5 | L5: =G5*Premissas!$B$5+J5*Premissas!$B$6/12 | M5: =K5*INDEX(Premissas!$B$29:$F$29,1,B5)+INDEX(Premissas!$B$27:$F$27,1,B5)*Premissas!$B$15/12+INDEX(Premissas!$B$28:$F$28,1,B5)*Premissas!$B$16 | N5: =L5+M5 | O5: =L5*Premissas!$B$8 | P5: =N5*Premissas!$B$9 | Q5: =N5-O5-P5 | R5: =K5*Premissas!$B$14 | S5: =INDEX(Premissas!$B$22:$F$22,1,B5) | T5: =INDEX(Premissas!$B$24:$F$24,1,B5) | U5: =INDEX(Premissas!$B$25:$F$25,1,B5) | V5: =INDEX(Premissas!$B$26:$F$26,1,B5) | W5: =Q5-R5-S5-T5-U5-V5 | X5: =X4+W5 | Y5: =S5/MAX(S5/INDEX(Premissas!$B$21:$F$21,1,B5)*Premissas!$B$10*Premissas!$B$11,1)
A6: 5 | B6: =INT((A6-1)/12)+1 | C6: =INDEX(Premissas!$B$22:$F$22,1,B6)/INDEX(Premissas!$B$21:$F$21,1,B6)*(1+INDEX(Premissas!$B$23:$F$23,1,B6)) | D6: =C6*Premissas!$B$10*Premissas!$B$11 | E6: =D6*(1-Premissas!$B$7) | F6: =D6*Premissas!$B$7 | G6: =G5*(1-Premissas!$B$12)+E6 | H6: 0 | I6: =F6+H6 | J6: =SUM(I2:I6) | K6: =G6+J6 | L6: =G6*Premissas!$B$5+J6*Premissas!$B$6/12 | M6: =K6*INDEX(Premissas!$B$29:$F$29,1,B6)+INDEX(Premissas!$B$27:$F$27,1,B6)*Premissas!$B$15/12+INDEX(Premissas!$B$28:$F$28,1,B6)*Premissas!$B$16 | N6: =L6+M6 | O6: =L6*Premissas!$B$8 | P6: =N6*Premissas!$B$9 | Q6: =N6-O6-P6 | R6: =K6*Premissas!$B$14 | S6: =INDEX(Premissas!$B$22:$F$22,1,B6) | T6: =INDEX(Premissas!$B$24:$F$24,1,B6) | U6: =INDEX(Premissas!$B$25:$F$25,1,B6) | V6: =INDEX(Premissas!$B$26:$F$26,1,B6) | W6: =Q6-R6-S6-T6-U6-V6 | X6: =X5+W6 | Y6: =S6/MAX(S6/INDEX(Premissas!$B$21:$F$21,1,B6)*Premissas!$B$10*Premissas!$B$11,1)
A7: 6 | B7: =INT((A7-1)/12)+1 | C7: =INDEX(Premissas!$B$22:$F$22,1,B7)/INDEX(Premissas!$B$21:$F$21,1,B7)*(1+INDEX(Premissas!$B$23:$F$23,1,B7)) | D7: =C7*Premissas!$B$10*Premissas!$B$11 | E7: =D7*(1-Premissas!$B$7) | F7: =D7*Premissas!$B$7 | G7: =G6*(1-Premissas!$B$12)+E7 | H7: 0 | I7: =F7+H7 | J7: =SUM(I2:I7) | K7: =G7+J7 | L7: =G7*Premissas!$B$5+J7*Premissas!$B$6/12 | M7: =K7*INDEX(Premissas!$B$29:$F$29,1,B7)+INDEX(Premissas!$B$27:$F$27,1,B7)*Premissas!$B$15/12+INDEX(Premissas!$B$28:$F$28,1,B7)*Premissas!$B$16 | N7: =L7+M7 | O7: =L7*Premissas!$B$8 | P7: =N7*Premissas!$B$9 | Q7: =N7-O7-P7 | R7: =K7*Premissas!$B$14 | S7: =INDEX(Premissas!$B$22:$F$22,1,B7) | T7: =INDEX(Premissas!$B$24:$F$24,1,B7) | U7: =INDEX(Premissas!$B$25:$F$25,1,B7) | V7: =INDEX(Premissas!$B$26:$F$26,1,B7) | W7: =Q7-R7-S7-T7-U7-V7 | X7: =X6+W7 | Y7: =S7/MAX(S7/INDEX(Premissas!$B$21:$F$21,1,B7)*Premissas!$B$10*Premissas!$B$11,1)
A8: 7 | B8: =INT((A8-1)/12)+1 | C8: =INDEX(Premissas!$B$22:$F$22,1,B8)/INDEX(Premissas!$B$21:$F$21,1,B8)*(1+INDEX(Premissas!$B$23:$F$23,1,B8)) | D8: =C8*Premissas!$B$10*Premissas!$B$11 | E8: =D8*(1-Premissas!$B$7) | F8: =D8*Premissas!$B$7 | G8: =G7*(1-Premissas!$B$12)+E8 | H8: 0 | I8: =F8+H8 | J8: =SUM(I2:I8) | K8: =G8+J8 | L8: =G8*Premissas!$B$5+J8*Premissas!$B$6/12 | M8: =K8*INDEX(Premissas!$B$29:$F$29,1,B8)+INDEX(Premissas!$B$27:$F$27,1,B8)*Premissas!$B$15/12+INDEX(Premissas!$B$28:$F$28,1,B8)*Premissas!$B$16 | N8: =L8+M8 | O8: =L8*Premissas!$B$8 | P8: =N8*Premissas!$B$9 | Q8: =N8-O8-P8 | R8: =K8*Premissas!$B$14 | S8: =INDEX(Premissas!$B$22:$F$22,1,B8) | T8: =INDEX(Premissas!$B$24:$F$24,1,B8) | U8: =INDEX(Premissas!$B$25:$F$25,1,B8) | V8: =INDEX(Premissas!$B$26:$F$26,1,B8) | W8: =Q8-R8-S8-T8-U8-V8 | X8: =X7+W8 | Y8: =S8/MAX(S8/INDEX(Premissas!$B$21:$F$21,1,B8)*Premissas!$B$10*Premissas!$B$11,1)
A9: 8 | B9: =INT((A9-1)/12)+1 | C9: =INDEX(Premissas!$B$22:$F$22,1,B9)/INDEX(Premissas!$B$21:$F$21,1,B9)*(1+INDEX(Premissas!$B$23:$F$23,1,B9)) | D9: =C9*Premissas!$B$10*Premissas!$B$11 | E9: =D9*(1-Premissas!$B$7) | F9: =D9*Premissas!$B$7 | G9: =G8*(1-Premissas!$B$12)+E9 | H9: 0 | I9: =F9+H9 | J9: =SUM(I2:I9) | K9: =G9+J9 | L9: =G9*Premissas!$B$5+J9*Premissas!$B$6/12 | M9: =K9*INDEX(Premissas!$B$29:$F$29,1,B9)+INDEX(Premissas!$B$27:$F$27,1,B9)*Premissas!$B$15/12+INDEX(Premissas!$B$28:$F$28,1,B9)*Premissas!$B$16 | N9: =L9+M9 | O9: =L9*Premissas!$B$8 | P9: =N9*Premissas!$B$9 | Q9: =N9-O9-P9 | R9: =K9*Premissas!$B$14 | S9: =INDEX(Premissas!$B$22:$F$22,1,B9) | T9: =INDEX(Premissas!$B$24:$F$24,1,B9) | U9: =INDEX(Premissas!$B$25:$F$25,1,B9) | V9: =INDEX(Premissas!$B$26:$F$26,1,B9) | W9: =Q9-R9-S9-T9-U9-V9 | X9: =X8+W9 | Y9: =S9/MAX(S9/INDEX(Premissas!$B$21:$F$21,1,B9)*Premissas!$B$10*Premissas!$B$11,1)
A10: 9 | B10: =INT((A10-1)/12)+1 | C10: =INDEX(Premissas!$B$22:$F$22,1,B10)/INDEX(Premissas!$B$21:$F$21,1,B10)*(1+INDEX(Premissas!$B$23:$F$23,1,B10)) | D10: =C10*Premissas!$B$10*Premissas!$B$11 | E10: =D10*(1-Premissas!$B$7) | F10: =D10*Premissas!$B$7 | G10: =G9*(1-Premissas!$B$12)+E10 | H10: 0 | I10: =F10+H10 | J10: =SUM(I2:I10) | K10: =G10+J10 | L10: =G10*Premissas!$B$5+J10*Premissas!$B$6/12 | M10: =K10*INDEX(Premissas!$B$29:$F$29,1,B10)+INDEX(Premissas!$B$27:$F$27,1,B10)*Premissas!$B$15/12+INDEX(Premissas!$B$28:$F$28,1,B10)*Premissas!$B$16 | N10: =L10+M10 | O10: =L10*Premissas!$B$8 | P10: =N10*Premissas!$B$9 | Q10: =N10-O10-P10 | R10: =K10*Premissas!$B$14 | S10: =INDEX(Premissas!$B$22:$F$22,1,B10) | T10: =INDEX(Premissas!$B$24:$F$24,1,B10) | U10: =INDEX(Premissas!$B$25:$F$25,1,B10) | V10: =INDEX(Premissas!$B$26:$F$26,1,B10) | W10: =Q10-R10-S10-T10-U10-V10 | X10: =X9+W10 | Y10: =S10/MAX(S10/INDEX(Premissas!$B$21:$F$21,1,B10)*Premissas!$B$10*Premissas!$B$11,1)
A11: 10 | B11: =INT((A11-1)/12)+1 | C11: =INDEX(Premissas!$B$22:$F$22,1,B11)/INDEX(Premissas!$B$21:$F$21,1,B11)*(1+INDEX(Premissas!$B$23:$F$23,1,B11)) | D11: =C11*Premissas!$B$10*Premissas!$B$11 | E11: =D11*(1-Premissas!$B$7) | F11: =D11*Premissas!$B$7 | G11: =G10*(1-Premissas!$B$12)+E11 | H11: 0 | I11: =F11+H11 | J11: =SUM(I2:I11) | K11: =G11+J11 | L11: =G11*Premissas!$B$5+J11*Premissas!$B$6/12 | M11: =K11*INDEX(Premissas!$B$29:$F$29,1,B11)+INDEX(Premissas!$B$27:$F$27,1,B11)*Premissas!$B$15/12+INDEX(Premissas!$B$28:$F$28,1,B11)*Premissas!$B$16 | N11: =L11+M11 | O11: =L11*Premissas!$B$8 | P11: =N11*Premissas!$B$9 | Q11: =N11-O11-P11 | R11: =K11*Premissas!$B$14 | S11: =INDEX(Premissas!$B$22:$F$22,1,B11) | T11: =INDEX(Premissas!$B$24:$F$24,1,B11) | U11: =INDEX(Premissas!$B$25:$F$25,1,B11) | V11: =INDEX(Premissas!$B$26:$F$26,1,B11) | W11: =Q11-R11-S11-T11-U11-V11 | X11: =X10+W11 | Y11: =S11/MAX(S11/INDEX(Premissas!$B$21:$F$21,1,B11)*Premissas!$B$10*Premissas!$B$11,1)
A12: 11 | B12: =INT((A12-1)/12)+1 | C12: =INDEX(Premissas!$B$22:$F$22,1,B12)/INDEX(Premissas!$B$21:$F$21,1,B12)*(1+INDEX(Premissas!$B$23:$F$23,1,B12)) | D12: =C12*Premissas!$B$10*Premissas!$B$11 | E12: =D12*(1-Premissas!$B$7) | F12: =D12*Premissas!$B$7 | G12: =G11*(1-Premissas!$B$12)+E12 | H12: 0 | I12: =F12+H12 | J12: =SUM(I2:I12) | K12: =G12+J12 | L12: =G12*Premissas!$B$5+J12*Premissas!$B$6/12 | M12: =K12*INDEX(Premissas!$B$29:$F$29,1,B12)+INDEX(Premissas!$B$27:$F$27,1,B12)*Premissas!$B$15/12+INDEX(Premissas!$B$28:$F$28,1,B12)*Premissas!$B$16 | N12: =L12+M12 | O12: =L12*Premissas!$B$8 | P12: =N12*Premissas!$B$9 | Q12: =N12-O12-P12 | R12: =K12*Premissas!$B$14 | S12: =INDEX(Premissas!$B$22:$F$22,1,B12) | T12: =INDEX(Premissas!$B$24:$F$24,1,B12) | U12: =INDEX(Premissas!$B$25:$F$25,1,B12) | V12: =INDEX(Premissas!$B$26:$F$26,1,B12) | W12: =Q12-R12-S12-T12-U12-V12 | X12: =X11+W12 | Y12: =S12/MAX(S12/INDEX(Premissas!$B$21:$F$21,1,B12)*Premissas!$B$10*Premissas!$B$11,1)
A13: 12 | B13: =INT((A13-1)/12)+1 | C13: =INDEX(Premissas!$B$22:$F$22,1,B13)/INDEX(Premissas!$B$21:$F$21,1,B13)*(1+INDEX(Premissas!$B$23:$F$23,1,B13)) | D13: =C13*Premissas!$B$10*Premissas!$B$11 | E13: =D13*(1-Premissas!$B$7) | F13: =D13*Premissas!$B$7 | G13: =G12*(1-Premissas!$B$12)+E13 | H13: 0 | I13: =F13+H13 | J13: =SUM(I2:I13) | K13: =G13+J13 | L13: =G13*Premissas!$B$5+J13*Premissas!$B$6/12 | M13: =K13*INDEX(Premissas!$B$29:$F$29,1,B13)+INDEX(Premissas!$B$27:$F$27,1,B13)*Premissas!$B$15/12+INDEX(Premissas!$B$28:$F$28,1,B13)*Premissas!$B$16 | N13: =L13+M13 | O13: =L13*Premissas!$B$8 | P13: =N13*Premissas!$B$9 | Q13: =N13-O13-P13 | R13: =K13*Premissas!$B$14 | S13: =INDEX(Premissas!$B$22:$F$22,1,B13) | T13: =INDEX(Premissas!$B$24:$F$24,1,B13) | U13: =INDEX(Premissas!$B$25:$F$25,1,B13) | V13: =INDEX(Premissas!$B$26:$F$26,1,B13) | W13: =Q13-R13-S13-T13-U13-V13 | X13: =X12+W13 | Y13: =S13/MAX(S13/INDEX(Premissas!$B$21:$F$21,1,B13)*Premissas!$B$10*Premissas!$B$11,1)
A14: 13 | B14: =INT((A14-1)/12)+1 | C14: =INDEX(Premissas!$B$22:$F$22,1,B14)/INDEX(Premissas!$B$21:$F$21,1,B14)*(1+INDEX(Premissas!$B$23:$F$23,1,B14)) | D14: =C14*Premissas!$B$10*Premissas!$B$11 | E14: =D14*(1-Premissas!$B$7) | F14: =D14*Premissas!$B$7 | G14: =G13*(1-Premissas!$B$12)+E14 | H14: =I2*Premissas!$B$13 | I14: =F14+H14 | J14: =SUM(I3:I14) | K14: =G14+J14 | L14: =G14*Premissas!$B$5+J14*Premissas!$B$6/12 | M14: =K14*INDEX(Premissas!$B$29:$F$29,1,B14)+INDEX(Premissas!$B$27:$F$27,1,B14)*Premissas!$B$15/12+INDEX(Premissas!$B$28:$F$28,1,B14)*Premissas!$B$16 | N14: =L14+M14 | O14: =L14*Premissas!$B$8 | P14: =N14*Premissas!$B$9 | Q14: =N14-O14-P14 | R14: =K14*Premissas!$B$14 | S14: =INDEX(Premissas!$B$22:$F$22,1,B14) | T14: =INDEX(Premissas!$B$24:$F$24,1,B14) | U14: =INDEX(Premissas!$B$25:$F$25,1,B14) | V14: =INDEX(Premissas!$B$26:$F$26,1,B14) | W14: =Q14-R14-S14-T14-U14-V14 | X14: =X13+W14 | Y14: =S14/MAX(S14/INDEX(Premissas!$B$21:$F$21,1,B14)*Premissas!$B$10*Premissas!$B$11,1)
A15: 14 | B15: =INT((A15-1)/12)+1 | C15: =INDEX(Premissas!$B$22:$F$22,1,B15)/INDEX(Premissas!$B$21:$F$21,1,B15)*(1+INDEX(Premissas!$B$23:$F$23,1,B15)) | D15: =C15*Premissas!$B$10*Premissas!$B$11 | E15: =D15*(1-Premissas!$B$7) | F15: =D15*Premissas!$B$7 | G15: =G14*(1-Premissas!$B$12)+E15 | H15: =I3*Premissas!$B$13 | I15: =F15+H15 | J15: =SUM(I4:I15) | K15: =G15+J15 | L15: =G15*Premissas!$B$5+J15*Premissas!$B$6/12 | M15: =K15*INDEX(Premissas!$B$29:$F$29,1,B15)+INDEX(Premissas!$B$27:$F$27,1,B15)*Premissas!$B$15/12+INDEX(Premissas!$B$28:$F$28,1,B15)*Premissas!$B$16 | N15: =L15+M15 | O15: =L15*Premissas!$B$8 | P15: =N15*Premissas!$B$9 | Q15: =N15-O15-P15 | R15: =K15*Premissas!$B$14 | S15: =INDEX(Premissas!$B$22:$F$22,1,B15) | T15: =INDEX(Premissas!$B$24:$F$24,1,B15) | U15: =INDEX(Premissas!$B$25:$F$25,1,B15) | V15: =INDEX(Premissas!$B$26:$F$26,1,B15) | W15: =Q15-R15-S15-T15-U15-V15 | X15: =X14+W15 | Y15: =S15/MAX(S15/INDEX(Premissas!$B$21:$F$21,1,B15)*Premissas!$B$10*Premissas!$B$11,1)
A16: 15 | B16: =INT((A16-1)/12)+1 | C16: =INDEX(Premissas!$B$22:$F$22,1,B16)/INDEX(Premissas!$B$21:$F$21,1,B16)*(1+INDEX(Premissas!$B$23:$F$23,1,B16)) | D16: =C16*Premissas!$B$10*Premissas!$B$11 | E16: =D16*(1-Premissas!$B$7) | F16: =D16*Premissas!$B$7 | G16: =G15*(1-Premissas!$B$12)+E16 | H16: =I4*Premissas!$B$13 | I16: =F16+H16 | J16: =SUM(I5:I16) | K16: =G16+J16 | L16: =G16*Premissas!$B$5+J16*Premissas!$B$6/12 | M16: =K16*INDEX(Premissas!$B$29:$F$29,1,B16)+INDEX(Premissas!$B$27:$F$27,1,B16)*Premissas!$B$15/12+INDEX(Premissas!$B$28:$F$28,1,B16)*Premissas!$B$16 | N16: =L16+M16 | O16: =L16*Premissas!$B$8 | P16: =N16*Premissas!$B$9 | Q16: =N16-O16-P16 | R16: =K16*Premissas!$B$14 | S16: =INDEX(Premissas!$B$22:$F$22,1,B16) | T16: =INDEX(Premissas!$B$24:$F$24,1,B16) | U16: =INDEX(Premissas!$B$25:$F$25,1,B16) | V16: =INDEX(Premissas!$B$26:$F$26,1,B16) | W16: =Q16-R16-S16-T16-U16-V16 | X16: =X15+W16 | Y16: =S16/MAX(S16/INDEX(Premissas!$B$21:$F$21,1,B16)*Premissas!$B$10*Premissas!$B$11,1)
A17: 16 | B17: =INT((A17-1)/12)+1 | C17: =INDEX(Premissas!$B$22:$F$22,1,B17)/INDEX(Premissas!$B$21:$F$21,1,B17)*(1+INDEX(Premissas!$B$23:$F$23,1,B17)) | D17: =C17*Premissas!$B$10*Premissas!$B$11 | E17: =D17*(1-Premissas!$B$7) | F17: =D17*Premissas!$B$7 | G17: =G16*(1-Premissas!$B$12)+E17 | H17: =I5*Premissas!$B$13 | I17: =F17+H17 | J17: =SUM(I6:I17) | K17: =G17+J17 | L17: =G17*Premissas!$B$5+J17*Premissas!$B$6/12 | M17: =K17*INDEX(Premissas!$B$29:$F$29,1,B17)+INDEX(Premissas!$B$27:$F$27,1,B17)*Premissas!$B$15/12+INDEX(Premissas!$B$28:$F$28,1,B17)*Premissas!$B$16 | N17: =L17+M17 | O17: =L17*Premissas!$B$8 | P17: =N17*Premissas!$B$9 | Q17: =N17-O17-P17 | R17: =K17*Premissas!$B$14 | S17: =INDEX(Premissas!$B$22:$F$22,1,B17) | T17: =INDEX(Premissas!$B$24:$F$24,1,B17) | U17: =INDEX(Premissas!$B$25:$F$25,1,B17) | V17: =INDEX(Premissas!$B$26:$F$26,1,B17) | W17: =Q17-R17-S17-T17-U17-V17 | X17: =X16+W17 | Y17: =S17/MAX(S17/INDEX(Premissas!$B$21:$F$21,1,B17)*Premissas!$B$10*Premissas!$B$11,1)
A18: 17 | B18: =INT((A18-1)/12)+1 | C18: =INDEX(Premissas!$B$22:$F$22,1,B18)/INDEX(Premissas!$B$21:$F$21,1,B18)*(1+INDEX(Premissas!$B$23:$F$23,1,B18)) | D18: =C18*Premissas!$B$10*Premissas!$B$11 | E18: =D18*(1-Premissas!$B$7) | F18: =D18*Premissas!$B$7 | G18: =G17*(1-Premissas!$B$12)+E18 | H18: =I6*Premissas!$B$13 | I18: =F18+H18 | J18: =SUM(I7:I18) | K18: =G18+J18 | L18: =G18*Premissas!$B$5+J18*Premissas!$B$6/12 | M18: =K18*INDEX(Premissas!$B$29:$F$29,1,B18)+INDEX(Premissas!$B$27:$F$27,1,B18)*Premissas!$B$15/12+INDEX(Premissas!$B$28:$F$28,1,B18)*Premissas!$B$16 | N18: =L18+M18 | O18: =L18*Premissas!$B$8 | P18: =N18*Premissas!$B$9 | Q18: =N18-O18-P18 | R18: =K18*Premissas!$B$14 | S18: =INDEX(Premissas!$B$22:$F$22,1,B18) | T18: =INDEX(Premissas!$B$24:$F$24,1,B18) | U18: =INDEX(Premissas!$B$25:$F$25,1,B18) | V18: =INDEX(Premissas!$B$26:$F$26,1,B18) | W18: =Q18-R18-S18-T18-U18-V18 | X18: =X17+W18 | Y18: =S18/MAX(S18/INDEX(Premissas!$B$21:$F$21,1,B18)*Premissas!$B$10*Premissas!$B$11,1)
A19: 18 | B19: =INT((A19-1)/12)+1 | C19: =INDEX(Premissas!$B$22:$F$22,1,B19)/INDEX(Premissas!$B$21:$F$21,1,B19)*(1+INDEX(Premissas!$B$23:$F$23,1,B19)) | D19: =C19*Premissas!$B$10*Premissas!$B$11 | E19: =D19*(1-Premissas!$B$7) | F19: =D19*Premissas!$B$7 | G19: =G18*(1-Premissas!$B$12)+E19 | H19: =I7*Premissas!$B$13 | I19: =F19+H19 | J19: =SUM(I8:I19) | K19: =G19+J19 | L19: =G19*Premissas!$B$5+J19*Premissas!$B$6/12 | M19: =K19*INDEX(Premissas!$B$29:$F$29,1,B19)+INDEX(Premissas!$B$27:$F$27,1,B19)*Premissas!$B$15/12+INDEX(Premissas!$B$28:$F$28,1,B19)*Premissas!$B$16 | N19: =L19+M19 | O19: =L19*Premissas!$B$8 | P19: =N19*Premissas!$B$9 | Q19: =N19-O19-P19 | R19: =K19*Premissas!$B$14 | S19: =INDEX(Premissas!$B$22:$F$22,1,B19) | T19: =INDEX(Premissas!$B$24:$F$24,1,B19) | U19: =INDEX(Premissas!$B$25:$F$25,1,B19) | V19: =INDEX(Premissas!$B$26:$F$26,1,B19) | W19: =Q19-R19-S19-T19-U19-V19 | X19: =X18+W19 | Y19: =S19/MAX(S19/INDEX(Premissas!$B$21:$F$21,1,B19)*Premissas!$B$10*Premissas!$B$11,1)
A20: 19 | B20: =INT((A20-1)/12)+1 | C20: =INDEX(Premissas!$B$22:$F$22,1,B20)/INDEX(Premissas!$B$21:$F$21,1,B20)*(1+INDEX(Premissas!$B$23:$F$23,1,B20)) | D20: =C20*Premissas!$B$10*Premissas!$B$11 | E20: =D20*(1-Premissas!$B$7) | F20: =D20*Premissas!$B$7 | G20: =G19*(1-Premissas!$B$12)+E20 | H20: =I8*Premissas!$B$13 | I20: =F20+H20 | J20: =SUM(I9:I20) | K20: =G20+J20 | L20: =G20*Premissas!$B$5+J20*Premissas!$B$6/12 | M20: =K20*INDEX(Premissas!$B$29:$F$29,1,B20)+INDEX(Premissas!$B$27:$F$27,1,B20)*Premissas!$B$15/12+INDEX(Premissas!$B$28:$F$28,1,B20)*Premissas!$B$16 | N20: =L20+M20 | O20: =L20*Premissas!$B$8 | P20: =N20*Premissas!$B$9 | Q20: =N20-O20-P20 | R20: =K20*Premissas!$B$14 | S20: =INDEX(Premissas!$B$22:$F$22,1,B20) | T20: =INDEX(Premissas!$B$24:$F$24,1,B20) | U20: =INDEX(Premissas!$B$25:$F$25,1,B20) | V20: =INDEX(Premissas!$B$26:$F$26,1,B20) | W20: =Q20-R20-S20-T20-U20-V20 | X20: =X19+W20 | Y20: =S20/MAX(S20/INDEX(Premissas!$B$21:$F$21,1,B20)*Premissas!$B$10*Premissas!$B$11,1)
A21: 20 | B21: =INT((A21-1)/12)+1 | C21: =INDEX(Premissas!$B$22:$F$22,1,B21)/INDEX(Premissas!$B$21:$F$21,1,B21)*(1+INDEX(Premissas!$B$23:$F$23,1,B21)) | D21: =C21*Premissas!$B$10*Premissas!$B$11 | E21: =D21*(1-Premissas!$B$7) | F21: =D21*Premissas!$B$7 | G21: =G20*(1-Premissas!$B$12)+E21 | H21: =I9*Premissas!$B$13 | I21: =F21+H21 | J21: =SUM(I10:I21) | K21: =G21+J21 | L21: =G21*Premissas!$B$5+J21*Premissas!$B$6/12 | M21: =K21*INDEX(Premissas!$B$29:$F$29,1,B21)+INDEX(Premissas!$B$27:$F$27,1,B21)*Premissas!$B$15/12+INDEX(Premissas!$B$28:$F$28,1,B21)*Premissas!$B$16 | N21: =L21+M21 | O21: =L21*Premissas!$B$8 | P21: =N21*Premissas!$B$9 | Q21: =N21-O21-P21 | R21: =K21*Premissas!$B$14 | S21: =INDEX(Premissas!$B$22:$F$22,1,B21) | T21: =INDEX(Premissas!$B$24:$F$24,1,B21) | U21: =INDEX(Premissas!$B$25:$F$25,1,B21) | V21: =INDEX(Premissas!$B$26:$F$26,1,B21) | W21: =Q21-R21-S21-T21-U21-V21 | X21: =X20+W21 | Y21: =S21/MAX(S21/INDEX(Premissas!$B$21:$F$21,1,B21)*Premissas!$B$10*Premissas!$B$11,1)
A22: 21 | B22: =INT((A22-1)/12)+1 | C22: =INDEX(Premissas!$B$22:$F$22,1,B22)/INDEX(Premissas!$B$21:$F$21,1,B22)*(1+INDEX(Premissas!$B$23:$F$23,1,B22)) | D22: =C22*Premissas!$B$10*Premissas!$B$11 | E22: =D22*(1-Premissas!$B$7) | F22: =D22*Premissas!$B$7 | G22: =G21*(1-Premissas!$B$12)+E22 | H22: =I10*Premissas!$B$13 | I22: =F22+H22 | J22: =SUM(I11:I22) | K22: =G22+J22 | L22: =G22*Premissas!$B$5+J22*Premissas!$B$6/12 | M22: =K22*INDEX(Premissas!$B$29:$F$29,1,B22)+INDEX(Premissas!$B$27:$F$27,1,B22)*Premissas!$B$15/12+INDEX(Premissas!$B$28:$F$28,1,B22)*Premissas!$B$16 | N22: =L22+M22 | O22: =L22*Premissas!$B$8 | P22: =N22*Premissas!$B$9 | Q22: =N22-O22-P22 | R22: =K22*Premissas!$B$14 | S22: =INDEX(Premissas!$B$22:$F$22,1,B22) | T22: =INDEX(Premissas!$B$24:$F$24,1,B22) | U22: =INDEX(Premissas!$B$25:$F$25,1,B22) | V22: =INDEX(Premissas!$B$26:$F$26,1,B22) | W22: =Q22-R22-S22-T22-U22-V22 | X22: =X21+W22 | Y22: =S22/MAX(S22/INDEX(Premissas!$B$21:$F$21,1,B22)*Premissas!$B$10*Premissas!$B$11,1)
A23: 22 | B23: =INT((A23-1)/12)+1 | C23: =INDEX(Premissas!$B$22:$F$22,1,B23)/INDEX(Premissas!$B$21:$F$21,1,B23)*(1+INDEX(Premissas!$B$23:$F$23,1,B23)) | D23: =C23*Premissas!$B$10*Premissas!$B$11 | E23: =D23*(1-Premissas!$B$7) | F23: =D23*Premissas!$B$7 | G23: =G22*(1-Premissas!$B$12)+E23 | H23: =I11*Premissas!$B$13 | I23: =F23+H23 | J23: =SUM(I12:I23) | K23: =G23+J23 | L23: =G23*Premissas!$B$5+J23*Premissas!$B$6/12 | M23: =K23*INDEX(Premissas!$B$29:$F$29,1,B23)+INDEX(Premissas!$B$27:$F$27,1,B23)*Premissas!$B$15/12+INDEX(Premissas!$B$28:$F$28,1,B23)*Premissas!$B$16 | N23: =L23+M23 | O23: =L23*Premissas!$B$8 | P23: =N23*Premissas!$B$9 | Q23: =N23-O23-P23 | R23: =K23*Premissas!$B$14 | S23: =INDEX(Premissas!$B$22:$F$22,1,B23) | T23: =INDEX(Premissas!$B$24:$F$24,1,B23) | U23: =INDEX(Premissas!$B$25:$F$25,1,B23) | V23: =INDEX(Premissas!$B$26:$F$26,1,B23) | W23: =Q23-R23-S23-T23-U23-V23 | X23: =X22+W23 | Y23: =S23/MAX(S23/INDEX(Premissas!$B$21:$F$21,1,B23)*Premissas!$B$10*Premissas!$B$11,1)
A24: 23 | B24: =INT((A24-1)/12)+1 | C24: =INDEX(Premissas!$B$22:$F$22,1,B24)/INDEX(Premissas!$B$21:$F$21,1,B24)*(1+INDEX(Premissas!$B$23:$F$23,1,B24)) | D24: =C24*Premissas!$B$10*Premissas!$B$11 | E24: =D24*(1-Premissas!$B$7) | F24: =D24*Premissas!$B$7 | G24: =G23*(1-Premissas!$B$12)+E24 | H24: =I12*Premissas!$B$13 | I24: =F24+H24 | J24: =SUM(I13:I24) | K24: =G24+J24 | L24: =G24*Premissas!$B$5+J24*Premissas!$B$6/12 | M24: =K24*INDEX(Premissas!$B$29:$F$29,1,B24)+INDEX(Premissas!$B$27:$F$27,1,B24)*Premissas!$B$15/12+INDEX(Premissas!$B$28:$F$28,1,B24)*Premissas!$B$16 | N24: =L24+M24 | O24: =L24*Premissas!$B$8 | P24: =N24*Premissas!$B$9 | Q24: =N24-O24-P24 | R24: =K24*Premissas!$B$14 | S24: =INDEX(Premissas!$B$22:$F$22,1,B24) | T24: =INDEX(Premissas!$B$24:$F$24,1,B24) | U24: =INDEX(Premissas!$B$25:$F$25,1,B24) | V24: =INDEX(Premissas!$B$26:$F$26,1,B24) | W24: =Q24-R24-S24-T24-U24-V24 | X24: =X23+W24 | Y24: =S24/MAX(S24/INDEX(Premissas!$B$21:$F$21,1,B24)*Premissas!$B$10*Premissas!$B$11,1)
A25: 24 | B25: =INT((A25-1)/12)+1 | C25: =INDEX(Premissas!$B$22:$F$22,1,B25)/INDEX(Premissas!$B$21:$F$21,1,B25)*(1+INDEX(Premissas!$B$23:$F$23,1,B25)) | D25: =C25*Premissas!$B$10*Premissas!$B$11 | E25: =D25*(1-Premissas!$B$7) | F25: =D25*Premissas!$B$7 | G25: =G24*(1-Premissas!$B$12)+E25 | H25: =I13*Premissas!$B$13 | I25: =F25+H25 | J25: =SUM(I14:I25) | K25: =G25+J25 | L25: =G25*Premissas!$B$5+J25*Premissas!$B$6/12 | M25: =K25*INDEX(Premissas!$B$29:$F$29,1,B25)+INDEX(Premissas!$B$27:$F$27,1,B25)*Premissas!$B$15/12+INDEX(Premissas!$B$28:$F$28,1,B25)*Premissas!$B$16 | N25: =L25+M25 | O25: =L25*Premissas!$B$8 | P25: =N25*Premissas!$B$9 | Q25: =N25-O25-P25 | R25: =K25*Premissas!$B$14 | S25: =INDEX(Premissas!$B$22:$F$22,1,B25) | T25: =INDEX(Premissas!$B$24:$F$24,1,B25) | U25: =INDEX(Premissas!$B$25:$F$25,1,B25) | V25: =INDEX(Premissas!$B$26:$F$26,1,B25) | W25: =Q25-R25-S25-T25-U25-V25 | X25: =X24+W25 | Y25: =S25/MAX(S25/INDEX(Premissas!$B$21:$F$21,1,B25)*Premissas!$B$10*Premissas!$B$11,1)
... A61: 60 | B61: =INT((A61-1)/12)+1 | C61: =INDEX(Premissas!$B$22:$F$22,1,B61)/INDEX(Premissas!$B$21:$F$21,1,B61)*(1+INDEX(Premissas!$B$23:$F$23,1,B61)) | D61: =C61*Premissas!$B$10*Premissas!$B$11 | E61: =D61*(1-Premissas!$B$7) | F61: =D61*Premissas!$B$7 | G61: =G60*(1-Premissas!$B$12)+E61 | H61: =I49*Premissas!$B$13 | I61: =F61+H61 | J61: =SUM(I50:I61) | K61: =G61+J61 | L61: =G61*Premissas!$B$5+J61*Premissas!$B$6/12 | M61: =K61*INDEX(Premissas!$B$29:$F$29,1,B61)+INDEX(Premissas!$B$27:$F$27,1,B61)*Premissas!$B$15/12+INDEX(Premissas!$B$28:$F$28,1,B61)*Premissas!$B$16 | N61: =L61+M61 | O61: =L61*Premissas!$B$8 | P61: =N61*Premissas!$B$9 | Q61: =N61-O61-P61 | R61: =K61*Premissas!$B$14 | S61: =INDEX(Premissas!$B$22:$F$22,1,B61) | T61: =INDEX(Premissas!$B$24:$F$24,1,B61) | U61: =INDEX(Premissas!$B$25:$F$25,1,B61) | V61: =INDEX(Premissas!$B$26:$F$26,1,B61) | W61: =Q61-R61-S61-T61-U61-V61 | X61: =X60+W61 | Y61: =S61/MAX(S61/INDEX(Premissas!$B$21:$F$21,1,B61)*Premissas!$B$10*Premissas!$B$11,1)

Sheet Cenários
A1: Cenários (calculados por business-plan/model.py)
A3: Indicador | B3: Conservador | C3: Base | D3: Otimista
A4: Assinantes ativos — ano 5 | B4: 69589.079 | C4: 125827.53 | D4: 195912.49
A5: Receita bruta — ano 5 | B5: 16389356 | C5: 28209674 | D5: 42967352
A6: EBITDA — ano 3 | B6: -870059.72 | C6: 1962596.2 | D6: 5238828
A7: EBITDA — ano 5 | B7: 952365.78 | C7: 9492488.3 | D7: 20170547
A8: Necessidade de caixa | B8: 2759356.2 | C8: 607585.65 | D8: 211463.53
A9: Mês de EBITDA positivo (a partir do ano 2) | B9: 35 | C9: 19 | D9: 16
A10: LTV por assinante | B10: 172.16969 | C10: 205.0421 | D10: 249.50879
A12: Conservador: teste→pago 25%, churn 16%, renovação 25%. Otimista: 55%, 9%, 45%. Demais premissas iguais à base.

Sheet Fontes
A1: Dado | B1: Fonte | C1: Link
A2: Mercado de beleza BR ~R$ 200 bi (2025); 3º maior do mundo | B2: ABIHPEC | C2: https://abihpec.org.br/tamanho-mercado-cosmeticos-brasil-2026/
A3: Beleza BR R$ 186,9 bi em 2025, +6,8% | B3: Euromonitor via Folha do Litoral | C3: https://folhadolitoral.com.br/editorias/economia/mercado-de-beleza-no-brasil-cresce-em-2025/
A4: Dermocosméticos R$ 12,3 bi (12m até jul/25), +8,3%; 83% em loja física | B4: IQVIA via Panorama Farmacêutico | C4: https://panoramafarmaceutico.com.br/mercado-de-dermocosmeticos-movimenta-r-123-bilhoes/
A5: Apps de análise de pele US$ 1,82 bi (2025), CAGR 17,2% até 2036 | B5: Future Market Insights | C5: https://www.futuremarketinsights.com/reports/skin-analysis-mobile-apps-market
A6: 88% das mulheres e 64% dos homens usam skincare | B6: MindMiners (2024) via O Hoje | C6: https://ohoje.com/2025/02/27/skincare-o-novo-vicio-dos-brasileiros/
A7: 23% usam assistentes de IA para escolher beleza; influenciadores 32% da descoberta | B7: Mercado & Consumo (out/2026) | C7: https://mercadoeconsumo.com.br/07/10/2026/noticias-varejo/seis-em-cada-dez-brasileiros-gastam-mais-de-r-100-por-mes-com-beleza/
A8: Teste→pago mediana Saúde & Fitness 39,9%; 2x maior no iOS | B8: RevenueCat — State of Subscription Apps 2025 | C8: https://revenuecat.com/state-of-subscription-apps-2025
A9: Cal AI: ~US$ 30 mi ARR, adquirido pela MyFitnessPal (2025/26) | B9: Imprensa (não auditado) | C9: https://neuronfeed.com/startups/cal-ai
A10: Skan: soft paywall, anual US$ 24,99–39,99 | B10: App Store / AppPricingLab | C10: https://apppricinglab.com/app/apple/6449196562
A11: Meta repassa 12,15% de impostos ao anunciante no BR | B11: Tecnoblog | C11: https://tecnoblog.net/noticias/meta-decide-repassar-os-custos-com-impostos-no-brasil-para-os-anunciantes/
A12: Beautytechs BR: B4A captou R$ 15 mi; UAUBox seed R$ 6 mi | B12: Startupi / Startups | C12: https://startupi.com.br/b4a-capta-r-15-milhoes-para-expandir-parcerias/
A13: 216 reviews de 9 apps concorrentes (dores e pedidos) | B13: Pesquisa própria | C13: replica/fixes.md
